chrono.py
chrono-1.0.2.dist-info/DESCRIPTION.rst
chrono-1.0.2.dist-info/METADATA
chrono-1.0.2.dist-info/pydist.json
chrono-1.0.2.dist-info/RECORD
chrono-1.0.2.dist-info/top_level.txt
chrono-1.0.2.dist-info/WHEEL
