Metadata-Version: 1.1
Name: chrono
Version: 1.0.2
Summary: A (BSD licensed) context manager for timing execution.
Home-page: https://github.com/toastdriven/chrono
Author: Daniel Lindsley
Author-email: daniel@toastdriven.com
License: BSD
Platform: UNKNOWN
Classifier: Development Status :: 5 - Production/Stable
Classifier: Intended Audience :: Developers
Classifier: License :: OSI Approved :: BSD License
Classifier: Operating System :: OS Independent
Classifier: Programming Language :: Python
Classifier: Programming Language :: Python :: 2
Classifier: Programming Language :: Python :: 3
